{
	"id": "error_partial_response",
	"description": "Handles incomplete or truncated HTTP response",
	"tags": [
		"error",
		"network"
	],
	"input": {
		"mock_responses": [
			{
				"status_code": 200,
				"headers": {
					"content-type": "text/html; charset=utf-8",
					"content-length": "99999",
					"connection": "close"
				},
				"body_inline": "<html><body><h1>Truncated"
			}
		],
		"config": {
			"respect_robots_txt": false
		}
	},
	"assertions": [
		{
			"type": "error"
		},
		{
			"type": "error",
			"value": "data_loss"
		}
	]
}
